examples/__init__.py
examples/usb-external-monitor/__init__.py
examples/usb-external-monitor/sample_count_down_timer.py
examples/usb-external-monitor/sample_number_animation.py
examples/usb-external-monitor/sample_number_effect.py
external_counter/__init__.py
external_counter/external_counter.py
external_counter_dilshan-1.0.4.data/scripts/usb-display-module-config
external_counter_dilshan-1.0.4.dist-info/LICENSE
external_counter_dilshan-1.0.4.dist-info/METADATA
external_counter_dilshan-1.0.4.dist-info/WHEEL
external_counter_dilshan-1.0.4.dist-info/top_level.txt
external_counter_dilshan-1.0.4.dist-info/RECORD
