Metadata-Version: 2.1
Name: external-counter-dilshan
Version: 1.0.4
Summary: Python API for USB seven segment display module
Home-page: https://github.com/dilshan/usb-external-display-python
Author: Dilshan R Jayakody
Author-email: jayakody2000lk@gmail.com
License: UNKNOWN
Platform: UNKNOWN
Classifier: Programming Language :: Python :: 3.6
Classifier: License :: OSI Approved :: MIT License
Classifier: Operating System :: Microsoft :: Windows
Classifier: Operating System :: POSIX :: Linux
Classifier: Operating System :: MacOS
Classifier: Topic :: System :: Hardware
Classifier: Intended Audience :: Developers
Classifier: Natural Language :: English
Requires-Dist: pyserial
